healthviz/__init__.py
healthviz/analysis.py
healthviz/data_handling.py
healthviz/visualization.py
tests/__init__.py
tests/test_analysis.py
tests/test_data_handling.py
tests/test_plotting.py
tests/test_visualization.py
healthviz-0.1.1.dist-info/LICENSE
healthviz-0.1.1.dist-info/METADATA
healthviz-0.1.1.dist-info/WHEEL
healthviz-0.1.1.dist-info/top_level.txt
healthviz-0.1.1.dist-info/RECORD
