Metadata-Version: 2.1
Name: healthviz
Version: 0.1.1
Summary: A package for health data visualization and analysis
Home-page: https://github.com/Saunakghosh10
Author: Saunak Ghosh
Author-email: saunakofficial10@gmail.com
License: MIT
Classifier: Programming Language :: Python :: 3
Classifier: License :: OSI Approved :: MIT License
Classifier: Operating System :: OS Independent
Requires-Python: >=3.6
License-File: LICENSE
Requires-Dist: pandas
Requires-Dist: matplotlib
Requires-Dist: seaborn
